cuba-0.0.1.dist-info/RECORD
cuba-0.0.1.dist-info/METADATA
cuba-0.0.1.dist-info/metadata.json
cuba-0.0.1.dist-info/top_level.txt
cuba-0.0.1.dist-info/WHEEL
cuba-0.0.1.dist-info/DESCRIPTION.rst
cuba/app.py
cuba/__init__.py
cuba/decorators.py
cuba/types.py
cuba/views.py
cuba/middlewares.py
cuba/inspect.py
cuba/exceptions.py
cuba/routes.py
cuba/shortcuts.py
cuba/tests/test_routes.py
cuba/tests/__init__.py
cuba/tests/base.py
cuba/tests/test_inspect.py
