Metadata-Version: 2.0
Name: cuba
Version: 0.0.1
Summary: Modern web framework that uses brand new Python 3.x features
Home-page: https://github.com/dveselov/cuba
Author: Dima Veselov
Author-email: d.a.veselov@yandex.ru
License: MIT
Keywords: web framework asyncio
Platform: UNKNOWN
Classifier: Development Status :: 3 - Alpha
Classifier: Topic :: Internet :: WWW/HTTP
Classifier: Intended Audience :: Developers
Classifier: License :: OSI Approved :: MIT License
Classifier: Programming Language :: Python :: 3
Classifier: Programming Language :: Python :: 3.3
Classifier: Programming Language :: Python :: 3.4
